NumRender/__init__.py
NumRender/number_converter.py
numrender-0.1.1.dist-info/licenses/LICENSE
tests/__init__.py
tests/test_number_converter.py
numrender-0.1.1.dist-info/METADATA
numrender-0.1.1.dist-info/WHEEL
numrender-0.1.1.dist-info/top_level.txt
numrender-0.1.1.dist-info/RECORD
