Metadata-Version: 2.4
Name: NumRender
Version: 0.1.1
Summary: A library to convert numbers to words and vice versa
Home-page: https://github.com/apih99/NumRender
Author: Shahrul Hafiz
Author-email: hafizcr716@gmail.com
Classifier: Programming Language :: Python :: 3
Classifier: License :: OSI Approved :: MIT License
Classifier: Operating System :: OS Independent
Classifier: Intended Audience :: Developers
Classifier: Topic :: Software Development :: Libraries :: Python Modules
Requires-Python: >=3.6
License-File: LICENSE
Dynamic: author
Dynamic: author-email
Dynamic: classifier
Dynamic: description
Dynamic: description-content-type
Dynamic: home-page
Dynamic: license-file
Dynamic: requires-python
Dynamic: summary
